pyvaporation/__init__.py
pyvaporation/components/__init__.py
pyvaporation/components/component.py
pyvaporation/components/components.py
pyvaporation/conditions/__init__.py
pyvaporation/conditions/conditions.py
pyvaporation/diffusion_curve/__init__.py
pyvaporation/diffusion_curve/diffusion_curve.py
pyvaporation/experiments/__init__.py
pyvaporation/experiments/ideal.py
pyvaporation/membrane/__init__.py
pyvaporation/membrane/membrane.py
pyvaporation/mixtures/__init__.py
pyvaporation/mixtures/mixture.py
pyvaporation/mixtures/mixtures.py
pyvaporation/mixtures/uniquac_fitting.py
pyvaporation/optimizer/__init__.py
pyvaporation/optimizer/optimizer.py
pyvaporation/permeance/__init__.py
pyvaporation/permeance/permeance.py
pyvaporation/pervaporation/__init__.py
pyvaporation/pervaporation/pervaporation.py
pyvaporation/plotting/__init__.py
pyvaporation/plotting/plotting.py
pyvaporation/process/__init__.py
pyvaporation/process/process.py
pyvaporation/utils/__init__.py
pyvaporation/utils/utils.py
pyvaporation-1.2.1.dist-info/LICENSE.md
pyvaporation-1.2.1.dist-info/LICENSE.txt
pyvaporation-1.2.1.dist-info/METADATA
pyvaporation-1.2.1.dist-info/WHEEL
pyvaporation-1.2.1.dist-info/top_level.txt
pyvaporation-1.2.1.dist-info/RECORD
