Metadata-Version: 2.1
Name: pyvaporation
Version: 1.2.1
Summary: Set of tools for modelling pervaporation processes
Home-page: https://github.com/Membrizard/PyVaporation
Download-URL: https://github.com/Membrizard/PyVaporation/archive/refs/tags/v1.1.5.tar.gz
Author: Denis Sapegin, Aleksei Chekmachev
Author-email: dasapegin@sr-systems.ru
License: Apache license 2.0
Keywords: pervaporation,membrane,chemistry,modelling,chemical-engineering,scientific
Classifier: Development Status :: 3 - Alpha
Classifier: Intended Audience :: Developers
Classifier: Topic :: Software Development :: Build Tools
Classifier: License :: OSI Approved :: Apache Software License
Classifier: Programming Language :: Python :: 3.7
Classifier: Programming Language :: Python :: 3.8
Classifier: Programming Language :: Python :: 3.9
Classifier: Programming Language :: Python :: 3.10
License-File: LICENSE.md
License-File: LICENSE.txt
Requires-Dist: joblib (==1.1.0)
Requires-Dist: matplotlib (==3.5.2)
Requires-Dist: pandas (==1.3.5)
Requires-Dist: scipy (==1.7.3)
Requires-Dist: attr (==0.3.1)
Requires-Dist: attrs (==21.4.0)
